peakrdl_bsv-0.0.1.dist-info/METADATA
peakrdl_bsv-0.0.1.dist-info/WHEEL
peakrdl_bsv-0.0.1.dist-info/entry_points.txt
peakrdl_bsv-0.0.1.dist-info/licenses/LICENSE
peakrdl_bsv/__init__.py
peakrdl_bsv/__peakrdl__.py
peakrdl_bsv/cli.py
peakrdl_bsv/exporter.py
peakrdl_bsv/print_bsv_csr.py
peakrdl_bsv/print_bsv_reg.py
peakrdl_bsv/print_bsv_signal.py
peakrdl_bsv/templates/__init__.py
peakrdl_bsv/templates/config_signal.bsv
peakrdl_bsv-0.0.1.dist-info/RECORD
