Metadata-Version: 2.1
Name: peakrdl_bsv
Version: 0.0.1
Summary: Export BSV description from the systemrdl-compiler register model
Author-Email: Vijayvithal Jahagirdar <jahagirdar.vs@gmail.com>
License: MIT
Classifier: Development Status :: 5 - Production/Stable
Classifier: Intended Audience :: Developers
Classifier: Operating System :: OS Independent
Classifier: Topic :: Scientific/Engineering :: Electronic Design Automation (EDA)
Project-URL: Homepage, https://dyumnin.com/peakrdl_bsv
Project-URL: Repository, https://github.com/jahagirdar/peakrdl-bsv.git
Project-URL: Issues, https://github.com/jahagirdar/peakrdl-bsv/issues
Project-URL: Documentation, https://jahagirdar.github.io/peakrdl-bsv
Requires-Python: >=3.10
Requires-Dist: systemrdl-compiler>=1.27.3
Requires-Dist: jinja2>=3.1.4
Requires-Dist: peakrdl>=1.1.0
